qnta/.gitkeep
qnta/__init__.py
qnta/qnta.py
qnta/utils/__init__.py
qnta/utils/util.py
qnta-0.0.6.dist-info/LICENSE
qnta-0.0.6.dist-info/METADATA
qnta-0.0.6.dist-info/WHEEL
qnta-0.0.6.dist-info/entry_points.txt
qnta-0.0.6.dist-info/RECORD
