Metadata-Version: 2.1
Name: qnta
Version: 0.0.6
Summary: Σ in innovation, harmony in finance
License: GPLv3
Author: CtrlX
Author-email: gitctrlx@gmail.com
Requires-Python: >=3.11,<4.0
Classifier: License :: Other/Proprietary License
Classifier: Programming Language :: Python :: 3
Classifier: Programming Language :: Python :: 3.11
Classifier: Programming Language :: Python :: 3.12
Classifier: Programming Language :: Python :: 3.13
Requires-Dist: art (>=6.4,<7.0)
Requires-Dist: copier (>=9.4.1,<10.0.0)
Requires-Dist: loguru (>=0.7.2,<0.8.0)
Requires-Dist: typer (>=0.12.5,<0.13.0)
